hackcheck-3.0.3.dist-info/METADATA
hackcheck-3.0.3.dist-info/WHEEL
hackcheck-3.0.3.dist-info/licenses/LICENSE
hackcheck/__init__.py
hackcheck/client.py
hackcheck/endpoints.py
hackcheck/errors.py
hackcheck/types.py
hackcheck-3.0.3.dist-info/RECORD
