Metadata-Version: 2.1
Name: hackcheck
Version: 3.0.3
Summary: Official python API wrapper for hackcheck.io
Author-Email: HackCheck <support@hackcheck.io>
License: MIT
Requires-Python: >=3.10
Requires-Dist: httpx>=0.26.0
Requires-Dist: pyserde>=0.12.7
